MANIFEST.in
README.md
meta.json
setup.py
en_prompt_nsfw_pipeline_char_embed/__init__.py
en_prompt_nsfw_pipeline_char_embed/meta.json
en_prompt_nsfw_pipeline_char_embed.egg-info/PKG-INFO
en_prompt_nsfw_pipeline_char_embed.egg-info/SOURCES.txt
en_prompt_nsfw_pipeline_char_embed.egg-info/dependency_links.txt
en_prompt_nsfw_pipeline_char_embed.egg-info/entry_points.txt
en_prompt_nsfw_pipeline_char_embed.egg-info/not-zip-safe
en_prompt_nsfw_pipeline_char_embed.egg-info/requires.txt
en_prompt_nsfw_pipeline_char_embed.egg-info/top_level.txt
en_prompt_nsfw_pipeline_char_embed/en_prompt_nsfw_pipeline_char_embed-0.3.0/config.cfg
en_prompt_nsfw_pipeline_char_embed/en_prompt_nsfw_pipeline_char_embed-0.3.0/meta.json
en_prompt_nsfw_pipeline_char_embed/en_prompt_nsfw_pipeline_char_embed-0.3.0/tokenizer
en_prompt_nsfw_pipeline_char_embed/en_prompt_nsfw_pipeline_char_embed-0.3.0/textcat/cfg
en_prompt_nsfw_pipeline_char_embed/en_prompt_nsfw_pipeline_char_embed-0.3.0/textcat/model
en_prompt_nsfw_pipeline_char_embed/en_prompt_nsfw_pipeline_char_embed-0.3.0/tok2vec/cfg
en_prompt_nsfw_pipeline_char_embed/en_prompt_nsfw_pipeline_char_embed-0.3.0/tok2vec/model
en_prompt_nsfw_pipeline_char_embed/en_prompt_nsfw_pipeline_char_embed-0.3.0/vocab/key2row
en_prompt_nsfw_pipeline_char_embed/en_prompt_nsfw_pipeline_char_embed-0.3.0/vocab/lookups.bin
en_prompt_nsfw_pipeline_char_embed/en_prompt_nsfw_pipeline_char_embed-0.3.0/vocab/strings.json
en_prompt_nsfw_pipeline_char_embed/en_prompt_nsfw_pipeline_char_embed-0.3.0/vocab/vectors
en_prompt_nsfw_pipeline_char_embed/en_prompt_nsfw_pipeline_char_embed-0.3.0/vocab/vectors.cfg